sr29/SR29.c
sr29/SR29.cp310-win_amd64.pyd
sr29/__init__.py
sr29/base.c
sr29/base.cp310-win_amd64.pyd
sr29/sr29Exception.py
SR29-1.0.4.dist-info/LICENSE
SR29-1.0.4.dist-info/METADATA
SR29-1.0.4.dist-info/NOTICE
SR29-1.0.4.dist-info/WHEEL
SR29-1.0.4.dist-info/entry_points.txt
SR29-1.0.4.dist-info/top_level.txt
SR29-1.0.4.dist-info/RECORD
