Metadata-Version: 2.1
Name: SR29
Version: 1.0.4
Summary: The SR29 encode and decode
Author: Mame29
License: Apache License 2.0
Classifier: Development Status :: 5 - Production/Stable
Classifier: Programming Language :: Python :: 3
Classifier: License :: OSI Approved :: Apache Software License
Classifier: Operating System :: OS Independent
License-File: LICENSE
License-File: NOTICE
Requires-Dist: progress
